pureapi/__init__.py
pureapi/app.py
pureapi/exceptions.py
pureapi/openapi.py
pureapi/request.py
pureapi/response.py
pureapi/routing.py
pureapi-0.1.1.dist-info/licenses/LICENSE
pureapi-0.1.1.dist-info/METADATA
pureapi-0.1.1.dist-info/WHEEL
pureapi-0.1.1.dist-info/top_level.txt
pureapi-0.1.1.dist-info/RECORD
