Metadata-Version: 2.4
Name: pureapi
Version: 0.1.1
Summary: A lightweight and elegant Python web framework
Author: MarkHoo
License: MIT
Project-URL: Homepage, https://github.com/MarkHoo/pureapi
Project-URL: Documentation, https://github.com/MarkHoo/pureapi/tree/main/docs
Project-URL: Repository, https://github.com/MarkHoo/pureapi
Keywords: web,framework,api,rest,openapi,swagger
Classifier: Development Status :: 4 - Beta
Classifier: Environment :: Web Environment
Classifier: Intended Audience :: Developers
Classifier: License :: OSI Approved :: MIT License
Classifier: Operating System :: OS Independent
Classifier: Programming Language :: Python :: 3
Classifier: Programming Language :: Python :: 3.10
Classifier: Programming Language :: Python :: 3.11
Classifier: Programming Language :: Python :: 3.12
Classifier: Programming Language :: Python :: 3.13
Classifier: Programming Language :: Python :: 3.14
Classifier: Topic :: Internet :: WWW/HTTP :: HTTP Servers
Classifier: Topic :: Internet :: WWW/HTTP :: WSGI :: Application
Classifier: Topic :: Software Development :: Libraries :: Application Frameworks
Requires-Python: >=3.10
License-File: LICENSE
Provides-Extra: dev
Requires-Dist: pytest>=7.0; extra == "dev"
Requires-Dist: pytest-cov>=4.0; extra == "dev"
Dynamic: license-file
